{
  "term": "Fall",
  "year": "2004",
  "level": [
    "Graduate"
  ],
  "topics": [
    [
      "Engineering",
      "Environmental Engineering"
    ],
    [
      "Business",
      "Information Technology"
    ],
    [
      "Engineering",
      "Computer Science",
      "Data Mining"
    ],
    [
      "Social Science",
      "Geography"
    ]
  ],
  "legacy_uid": "4032baef-3967-0dcb-ee87-f3b7c9d29ba9",
  "instructors": {
    "content": [
      "af384539-917b-cd05-a44a-7c235805dd84"
    ],
    "website": "ocw-www"
  },
  "course_image": {
    "content": "c87498ea-277d-e033-1872-29bbf8dac9d6",
    "website": "1-963-environmental-engineering-applications-of-geographic-information-systems-fall-2004"
  },
  "course_title": "Environmental Engineering Applications of Geographic Information Systems",
  "course_description": "This graduate seminar is taught in a lecture and lab exercise format.\u00a0The subject matter is tailored to introduce Environmental Engineering students to the use and potential of Geographic Information Systems in their discipline. Lectures will cover the general concepts of GIS use and introduce the material in the exercises that demonstrate the practical application of GIS.\n",
  "department_numbers": [
    "1"
  ],
  "extra_course_numbers": "",
  "primary_course_number": "1.963",
  "course_image_thumbnail": {
    "content": "eb106993-9c0f-ecdf-4826-69f2d5305770",
    "website": "1-963-environmental-engineering-applications-of-geographic-information-systems-fall-2004"
  },
  "learning_resource_types": [
    "Lecture Notes"
  ],
  "site_uid": "b65b4a6c-56a0-455d-82ef-cbff73747a93",
  "site_short_id": "1.963-fall-2004",
  "site_url_path": "courses/1-963-environmental-engineering-applications-of-geographic-information-systems-fall-2004",
  "title": "Course Metadata"
}